test_archiver/ArchiverRobotListener.py
test_archiver/__init__.py
test_archiver/archiver.py
test_archiver/archiver_listeners.py
test_archiver/configs.py
test_archiver/database.py
test_archiver/output_parser.py
test_archiver/schemas/README.md
test_archiver/schemas/migrations/postgres/0001-schema_update_table_and_log_message_index.sql
test_archiver/schemas/migrations/postgres/0002-execution_paths.sql
test_archiver/schemas/migrations/postgres/0003-test_run_mapping_cascade.sql
test_archiver/schemas/migrations/sqlite/0001-schema_update_table_and_log_message_index.sql
test_archiver/schemas/migrations/sqlite/0002-execution_paths.sql
test_archiver/schemas/migrations/sqlite/0003-test_run_mapping_cascade.sql
test_archiver/schemas/migrations/sqlite/testing/10001-minor_test_update1.sql
test_archiver/schemas/migrations/sqlite/testing/10002-minor_test_update2.sql
test_archiver/schemas/migrations/sqlite/testing/10003-major_test_update.sql
test_archiver/schemas/schema_postgres.sql
test_archiver/schemas/schema_sqlite.sql
test_archiver/version.py
test_archiver/version.txt
testarchiver-4.1.0.dist-info/METADATA
testarchiver-4.1.0.dist-info/WHEEL
testarchiver-4.1.0.dist-info/entry_points.txt
testarchiver-4.1.0.dist-info/licenses/LICENSE
testarchiver-4.1.0.dist-info/RECORD
