Metadata-Version: 2.1
Name: testarchiver
Version: 4.1.0
Summary: Tools for serialising test results to SQL database
Author-Email: Tommi Oinonen <tommi.oinonen@siili.com>
License:                                  Apache License
Classifier: Programming Language :: Python :: 3
Classifier: Operating System :: OS Independent
Classifier: Topic :: Software Development :: Testing
Project-URL: Homepage, https://github.com/salabs/TestArchiver
Project-URL: Repository, https://github.com/salabs/TestArchiver
Project-URL: Issues, https://github.com/salabs/TestArchiver/issues
Requires-Python: >=3.9
Requires-Dist: psycopg2-binary>=2.8.5
